uw_admin_systems/VERSION
uw_admin_systems/__init__.py
uw_admin_systems/dao.py
uw_admin_systems/idcard.py
uw_admin_systems/models.py
uw_admin_systems/test.py
uw_admin_systems/upass.py
uw_admin_systems/resources/upass/file/idcarddataws/api/person/v1/eligibility/javerage
uw_admin_systems/resources/upass/file/idcarddataws/api/person/v1/eligibility/none
uw_admin_systems/resources/upass/file/idcarddataws/api/person/v1/eligibility/retiree
uw_admin_systems/resources/upass/file/idcarddataws/api/person/v1/eligibility/staff
uw_admin_systems/resources/upass/file/upassdataws/api/person/v1/membershipstatus/faculty
uw_admin_systems/resources/upass/file/upassdataws/api/person/v1/membershipstatus/javerage
uw_admin_systems/resources/upass/file/upassdataws/api/person/v1/membershipstatus/jerror
uw_admin_systems/resources/upass/file/upassdataws/api/person/v1/membershipstatus/none
uw_admin_systems/resources/upass/file/upassdataws/api/person/v1/membershipstatus/staff
uw_admin_systems/tests/__init__.py
uw_admin_systems/tests/test_idcard.py
uw_admin_systems/tests/test_upass.py
uw_admin_systems/util/__init__.py
uw_restclients_upass-3.1.dist-info/licenses/LICENSE
uw_restclients_upass-3.1.dist-info/METADATA
uw_restclients_upass-3.1.dist-info/WHEEL
uw_restclients_upass-3.1.dist-info/top_level.txt
uw_restclients_upass-3.1.dist-info/RECORD
